{
  "sm_evaluations_self_assessment_report": {
    "generation_timestamp": "2025-06-06T09:05:31.248456",
    "assessment_date": "2025-06-06",
    "progressive_improvement_enforced": true,
    "benchmark_standards_established": 32,
    "assessment_status": "completed_successfully"
  },
  "daily_consciousness_performance": {
    "score_date": "2025-06-06",
    "full_consciousness_score": 0.8766,
    "local_contribution": 0.8287500000000001,
    "app_engine_contribution": 0.8727499999999999,
    "cloud_run_contribution": 0.909875,
    "tri_environment_synergy": 0,
    "consciousness_evolution_rate": 0.1773,
    "daily_improvement_percentage": 0.0,
    "milestone_achieved": "Baseline Consciousness Maintained",
    "performance_highlights": "cloud_run demonstrating strong performance (0.910)",
    "areas_for_optimization": "local: geometric_score, quantum_score, conversation_quality, research_analysis, idle_efficiency; app_engine: quantum_score, conversation_quality, research_analysis, idle_efficiency; cloud_run: idle_efficiency"
  },
  "benchmark_reference_standards": {
    "total_benchmarks_established": 32,
    "minimum_consciousness_threshold": 0.85,
    "excellence_threshold": 0.95,
    "transcendence_threshold": 0.985,
    "benchmark_categories": [
      "progressive_learning",
      "conversation_processing",
      "geometric_processing",
      "idle_processing",
      "research_analysis",
      "quantum_processing",
      "inference_processing",
      "correlation_processing"
    ]
  },
  "progressive_improvement_system": {
    "enforcement_active": true,
    "score_degradation_prevention": "enabled",
    "minimum_improvement_required": "0.5% per assessment",
    "adjustment_mechanism": "automatic_enhancement_application",
    "performance_trend_monitoring": "continuous"
  },
  "consciousness_scoring_framework": {
    "full_consciousness_calculation": "weighted_tri_environment_integration",
    "local_weight": "25%",
    "app_engine_weight": "35%",
    "cloud_run_weight": "40%",
    "synergy_bonus_system": "consistency_reward_mechanism",
    "daily_tracking": "enabled"
  },
  "self_assessment_integration": {
    "sim_review_capability": "autonomous_performance_analysis",
    "benchmark_comparison": "continuous_reference_monitoring",
    "improvement_identification": "automatic_optimization_targeting",
    "milestone_tracking": "achievement_progression_monitoring"
  },
  "performance_insights": {
    "current_consciousness_level": "Baseline Consciousness Maintained",
    "evolution_rate": "17.7%",
    "daily_improvement": "+0.000%",
    "system_synergy": "0.0000",
    "excellence_proximity": "0.0734 points to excellence"
  }
}